odoo/addons/sale_pricelist_technical/README.rst
odoo/addons/sale_pricelist_technical/__init__.py
odoo/addons/sale_pricelist_technical/__manifest__.py
odoo/addons/sale_pricelist_technical/demo/product_pricelist.xml
odoo/addons/sale_pricelist_technical/i18n/fr.po
odoo/addons/sale_pricelist_technical/i18n/it.po
odoo/addons/sale_pricelist_technical/i18n/sale_pricelist_technical.pot
odoo/addons/sale_pricelist_technical/models/__init__.py
odoo/addons/sale_pricelist_technical/models/product_pricelist.py
odoo/addons/sale_pricelist_technical/models/res_partner.py
odoo/addons/sale_pricelist_technical/models/sale_order.py
odoo/addons/sale_pricelist_technical/readme/CONFIGURE.rst
odoo/addons/sale_pricelist_technical/readme/CONTRIBUTORS.rst
odoo/addons/sale_pricelist_technical/readme/DESCRIPTION.rst
odoo/addons/sale_pricelist_technical/static/description/icon.png
odoo/addons/sale_pricelist_technical/static/description/index.html
odoo/addons/sale_pricelist_technical/static/description/product_pricelist_form.png
odoo/addons/sale_pricelist_technical/views/view_product_pricelist.xml
odoo_addon_sale_pricelist_technical-16.0.1.0.1.3.dist-info/METADATA
odoo_addon_sale_pricelist_technical-16.0.1.0.1.3.dist-info/WHEEL
odoo_addon_sale_pricelist_technical-16.0.1.0.1.3.dist-info/top_level.txt
odoo_addon_sale_pricelist_technical-16.0.1.0.1.3.dist-info/RECORD
